druglinker/__init__.py
druglinker/dbsearch.py
druglinker/dbvocab.csv
druglinker-0.1.1.dist-info/LICENSE
druglinker-0.1.1.dist-info/METADATA
druglinker-0.1.1.dist-info/WHEEL
druglinker-0.1.1.dist-info/top_level.txt
druglinker-0.1.1.dist-info/RECORD
