Metadata-Version: 2.1
Name: druglinker
Version: 0.1.1
Summary: Simple drug linking
Home-page: https://github.com/fgh95/DrugLinker
Author: Ferran Gonzalez Hernandez
Author-email: ucbpfgo@ucl.ac.uk
License: MIT
Platform: UNKNOWN
Requires-Python: >=3.6
Requires-Dist: pandas (==1.0.3)
